RISCV32bit/Project_folder/Control/definition.vh
`ifndef DEFINITION
`define DEFINITION

`define R_type 7'b0110011
`define I_type_ALU 7'b0010011
`define I_type_LOAD 7'b0000011
`define S_type 7'b0100011
`define I_type_JALR 7'b1100111
`define B_type 7'b1100011
`define U_type_LUI 7'b0110111
`define U_type_AUIPC 7'b0010111

`endif

RISCV32bit/Project_folder/Control/Control.sv
import riscv_op_pkg::*;

module control_unit(
    input  logic [6:0] op,
    input  logic [2:0] funct3,
    input  logic [6:0] funct7,

    output logic       RegWriteD,
    output logic [1:0] ResultSrcD,
    output logic       MemWriteD,
    output logic       JumpD,
    output logic       BranchD,
    output logic [3:0] ALUControlD, // 오타 수정 (ALUContolD -> ALUControlD)
    output logic       ALUSrcD,
    output logic [2:0] ImmSrcD
);
    // Opcode만 enum.
    opcode_type op_type;
    assign op_type = opcode_type'(op);

    // 10-bit funct 조합 (R-type 및 I-type Shift 구분에 사용)
    wire [9:0] funct = {funct3, funct7};


    
    // ALU 연산 관련
    wire is_ALU_arith     = (op_type == R_type)     & ((funct == ADD) | (funct == SUB));
    wire is_ALU_arith_imm = (op_type == I_type_ALU) & (funct3 == F3_ADDI);
    
    // 비교 연산자(=) 누락 수정
    wire is_ALU_shift     = (op_type == R_type)     & ((funct == SLL)  | (funct == SRL)  | (funct == SRA));
    wire is_ALU_shift_imm = (op_type == I_type_ALU) & ((funct == SLLI) | (funct == SRLI) | (funct == SRAI));
    
    wire is_ALU_logic     = (op_type == R_type)     & ((funct == SLT) | (funct == SLTU) | (funct == XOR) | (funct == OR) | (funct == AND));
    wire is_ALU_logic_imm = (op_type == I_type_ALU) & ((funct3 == F3_SLTI) | (funct3 == F3_SLTIU) | (funct3 == F3_XORI) | (funct3 == F3_ORI) | (funct3 == F3_ANDI));

    // Load 및 Store 관련
    wire is_load  = (op_type == I_type_LOAD) & ((funct3 == F3_LB) | (funct3 == F3_LH) | (funct3 == F3_LW) | (funct3 == F3_LBU) | (funct3 == F3_LHU));
    wire is_store = (op_type == S_type)      & ((funct3 == F3_SB) | (funct3 == F3_SH) | (funct3 == F3_SW));
    
    // Branch 및 Jump 관련
    wire is_branch = (op_type == B_type) & ((funct3 == F3_BEQ) | (funct3 == F3_BNE) | (funct3 == F3_BLT) | (funct3 == F3_BGE) | (funct3 == F3_BLTU) | (funct3 == F3_BGEU));
    wire is_jump   = (op_type == I_type_JALR) | (op_type == J_type); // JAL도 Jump에 포함되도록 추가 권장

    // System 관련
    wire is_system = (op_type == System) & ((funct3 == F3_CSRRW) | (funct3 == F3_CSRRS) | (funct3 == F3_CSRRC) | (funct3 == F3_CSRRWI) | (funct3 == F3_CSRRSI) | (funct3 == F3_CSRRCI));

    // 기타 (추후 추가용)
    wire is_lui   = (op_type == U_type_LUI);
    wire is_auipc = (op_type == U_type_AUIPC);
    wire is_fence = (op_type == Fence);

    // -----------------------------------------------------------------------
    // 출력 제어 신호 할당
    // -----------------------------------------------------------------------

    assign RegWriteD  = (op_type == R_type) | (op_type == I_type_ALU) | (op_type == I_type_LOAD) | (op_type == I_type_JALR) | (op_type == J_type) | (op_type == U_type_AUIPC) | (op_type == U_type_LUI);
    assign ResultSrcD = ((op_type == I_type_ALU) | (op_type == R_type) | (op_type == U_type_LUI) | (op_type == U_type_AUIPC)) ? 2'b00 : 
                        (op_type == I_type_LOAD) ? 2'b01 : 
                        ((op_type == I_type_JALR) | (op_type == J_type)) ? 2'b10 : 2'b11;

    assign MemWriteD = is_store;
    assign JumpD     = is_jump;
    assign BranchD   = is_branch;
    

    assign ALUSrcD   = (op_type == I_type_ALU) | (op_type == I_type_LOAD) | (op_type == S_type) | (op_type == U_type_AUIPC);

    wire sel_arith_logic = (is_ALU_arith | is_ALU_arith_imm | ((op_type == R_type) & (funct == SRA)) | ((op_type == I_type_ALU) & (funct == SRAI)) | is_load | is_store | is_branch | is_jump);
    
    logic [2:0] alu_ctl;
    assign ALUControlD = {sel_arith_logic, alu_ctl};

    // ALU 제어 로직 (funct3, funct 직접 비교)
    always_comb begin
        alu_ctl = 3'b000;

        if (is_ALU_arith | is_ALU_logic) begin
            case(funct)
                ADD : alu_ctl = 3'b001;
                SUB : alu_ctl = 3'b010;
                SLT : alu_ctl = 3'b011;
                SLTU: alu_ctl = 3'b100;
                XOR : alu_ctl = 3'b101;
                OR  : alu_ctl = 3'b110;
                AND : alu_ctl = 3'b111;
                default: alu_ctl = 3'b000;
            endcase
        end
        else if (is_ALU_arith_imm | is_ALU_logic_imm) begin
            case(funct3)
                F3_ADDI : alu_ctl = 3'b001;
                F3_SLTI : alu_ctl = 3'b011;
                F3_SLTIU: alu_ctl = 3'b100;
                F3_XORI : alu_ctl = 3'b101;
                F3_ORI  : alu_ctl = 3'b110;
                F3_ANDI : alu_ctl = 3'b111;
                default : alu_ctl = 3'b000;
            endcase
        end
        else if (is_ALU_shift) begin
            case(funct)
                SLL : alu_ctl = 3'b001;
                SRL : alu_ctl = 3'b010;
                SRA : alu_ctl = 3'b100;
                default: alu_ctl = 3'b000;
            endcase
        end
        else if (is_ALU_shift_imm) begin
            case(funct)
                SLLI: alu_ctl = 3'b001;
                SRLI: alu_ctl = 3'b010;
                SRAI: alu_ctl = 3'b100;
                default: alu_ctl = 3'b000;
            endcase
        end
        else if (is_load) begin
            case(funct3)
                F3_LB, F3_LH, F3_LW, F3_LBU, F3_LHU: alu_ctl = 3'b001;
                default: alu_ctl = 3'b000;
            endcase
        end
        else if (is_store) begin
            case(funct3)
                F3_SB, F3_SH, F3_SW: alu_ctl = 3'b001;
                default: alu_ctl = 3'b000;
            endcase
        end
        else if (is_branch) begin
            case(funct3)
                F3_BEQ, F3_BNE, F3_BLT, F3_BGE, F3_BLTU, F3_BGEU: alu_ctl = 3'b001;
                default: alu_ctl = 3'b000;
            endcase
        end
        else if (is_system) begin
            case(funct3)
                F3_CSRRW, F3_CSRRS, F3_CSRRC, F3_CSRRWI, F3_CSRRSI, F3_CSRRCI: alu_ctl = 3'b001;
                default: alu_ctl = 3'b000;
            endcase
        end
        else if ((op_type == I_type_JALR) | (op_type == U_type_LUI) | (op_type == U_type_AUIPC) | is_fence) begin
            alu_ctl = 3'b001;
        end
    end
    
    logic [2:0] imm_ctl;
    assign ImmSrcD = imm_ctl;

    // ImmSrcD case문 에러 수정 (정확한 enum 사용)
    always_comb begin
        imm_ctl = 3'b000;
        case(op_type)
            I_type_ALU, I_type_LOAD, I_type_JALR : imm_ctl = 3'b001;
            S_type                               : imm_ctl = 3'b010;
            B_type                               : imm_ctl = 3'b011;
            U_type_LUI, U_type_AUIPC             : imm_ctl = 3'b100;
            J_type                               : imm_ctl = 3'b101;
            default                              : imm_ctl = 3'b000;
        endcase
    end

endmodule

RISCV32bit/Project_folder/Control/tb_Control.sv
`timescale 1ps/1ps
import riscv_op_pkg::*;
`include "definition.vh"

module tb_Control;

    // logic [6:0] op;
    // logic [2:0] funct3;
    // logic [6:0] funct7;

    logic RegWriteD;
    logic [1:0] ResultSrcD;
    logic MemWriteD;
    logic JumpD;
    logic BranchD;
    logic [3:0] ALUControlD;
    logic ALUSrcD;
    logic [2:0] ImmSrcD;



    typedef struct packed {
        logic [6:0] op;
        logic [2:0] funct3;
        logic [6:0] funct7;
    } input_list;

    input_list input_cases [36] = '{
        '{op : `R_type, funct3 : 3'b000, funct7 : 7'b0000000},   // R type ADD
        '{op : `R_type, funct3 : 3'b000, funct7 : 7'b0100000},   // R type SUB
        '{op : `R_type, funct3 : 3'b001, funct7 : 7'b0000000},   // R type SLL
        '{op : `R_type, funct3 : 3'b010, funct7 : 7'b0000000},   // R type SLT
        '{op : `R_type, funct3 : 3'b011, funct7 : 7'b0000000},   // R type SLTU
        '{op : `R_type, funct3 : 3'b100, funct7 : 7'b0000000},   // R type XOR
        '{op : `R_type, funct3 : 3'b101, funct7 : 7'b0000000},   // R type SRL
        '{op : `R_type, funct3 : 3'b101, funct7 : 7'b0100000},   // R type SRA
        '{op : `R_type, funct3 : 3'b110, funct7 : 7'b0000000},   // R type OR
        '{op : `R_type, funct3 : 3'b111, funct7 : 7'b0000000},   // R type AND


        '{op : `I_type_ALU, funct3 : 3'b000, funct7 : 7'b0000000},   // I type ALU ADDI
        '{op : `I_type_ALU, funct3 : 3'b010, funct7 : 7'b0000000},   // I type ALU SLTI
        '{op : `I_type_ALU, funct3 : 3'b011, funct7 : 7'b0000000},   // I type ALU SLTUI
        '{op : `I_type_ALU, funct3 : 3'b100, funct7 : 7'b0000000},   // I type ALU XORI
        '{op : `I_type_ALU, funct3 : 3'b110, funct7 : 7'b0000000},   // I type ALU ORI
        '{op : `I_type_ALU, funct3 : 3'b111, funct7 : 7'b0000000},   // I type ALU ANDI
        '{op : `I_type_ALU, funct3 : 3'b001, funct7 : 7'b0000000},   // I type ALU SLLI
        '{op : `I_type_ALU, funct3 : 3'b101, funct7 : 7'b0000000},   // I type ALU SRLI
        '{op : `I_type_ALU, funct3 : 3'b101, funct7 : 7'b0100000},   // I type ALU SRAI
        
        '{op : `I_type_LOAD, funct3 : 3'b000, funct7 : 7'b0000000},   // I type Load LB
        '{op : `I_type_LOAD, funct3 : 3'b001, funct7 : 7'b0000000},   // I type Load LH
        '{op : `I_type_LOAD, funct3 : 3'b010, funct7 : 7'b0000000},   // I type Load LW
        '{op : `I_type_LOAD, funct3 : 3'b100, funct7 : 7'b0000000},   // I type Load LBU
        '{op : `I_type_LOAD, funct3 : 3'b101, funct7 : 7'b0000000},   // I type Load LHU

        '{op : `S_type, funct3 : 3'b000, funct7 : 7'b0000000},   // S type STORE SB
        '{op : `S_type, funct3 : 3'b001, funct7 : 7'b0000000},   // S type STORE SH
        '{op : `S_type, funct3 : 3'b010, funct7 : 7'b0000000},   // S type STORE SW


        '{op : `I_type_JALR, funct3 : 3'b000, funct7 : 7'b0000000},   // I type JALR

        '{op : `B_type, funct3 : 3'b000, funct7 : 7'b0000000},   // B type BEQ
        '{op : `B_type, funct3 : 3'b001, funct7 : 7'b0000000},   // B type BNE
        '{op : `B_type, funct3 : 3'b100, funct7 : 7'b0000000},   // B type BLT
        '{op : `B_type, funct3 : 3'b101, funct7 : 7'b0000000},   // B type BGE
        '{op : `B_type, funct3 : 3'b110, funct7 : 7'b0000000},   // B type BLTU
        '{op : `B_type, funct3 : 3'b111, funct7 : 7'b0000000},   // B type BGEU

        '{op : `U_type_LUI, funct3 : 3'b000, funct7 : 7'b0000000},   // U type LUI
        '{op : `U_type_AUIPC, funct3 : 3'b000, funct7 : 7'b0000000}   // U type AUIPC
    };



    input_list real_input;

    control_unit dut(
        .op(real_input.op),
        .funct3(real_input.funct3),
        .funct7(real_input.funct7),

        .RegWriteD(RegWriteD),
        .ResultSrcD(ResultSrcD),
        .MemWriteD(MemWriteD),
        .JumpD(JumpD),
        .BranchD(BranchD),
        .ALUControlD(ALUControlD),
        .ALUSrcD(ALUSrcD),
        .ImmSrcD(ImmSrcD)
    );

    initial begin
        #3;

        $display("initializing...");

        #3;

        foreach (input_cases[i]) begin
            real_input = input_cases[i];
            $display("operation type : %0d, funct3 : %0b, funct7 : %0b", real_input.op, real_input.funct3, real_input.funct7);

            #2; 

            $display("Testing...");

            #4;

            $display("OUTPUT RESULT : Register Write : %0b, Result Select : %0b, Memory Write : %0b, JUMP : %0b, Branch : %0b, ALU Control : %0b, ALU Select : %0b, Immediate Value : %0b", RegWriteD, ResultSrcD, MemWriteD, JumpD, BranchD, ALUControlD, ALUSrcD, ImmSrcD);


            #1;
        end 

        #1;

        $finish;
    end
    initial begin
        $dumpfile("Pipeline_Controller_waveform.vcd");
        $dumpvars(0, dut);
    end
    

endmodule

RISCV32bit/Project_folder/Control/Controller_proj/Controller_proj.sim/sim_1/behav/xsim/Pipeline_Controller_waveform.vcd
$date
   Sat Apr  4 14:29:13 2026
$end

$version
  2025.1.0
  $dumpfile ("Pipeline_Controller_waveform.vcd") 
$end

$timescale
  1ps
$end

$scope module tb_Control $end
$scope module dut $end
$var wire 7 ! op [6:0] $end
$var wire 3 " funct3 [2:0] $end
$var wire 7 # funct7 [6:0] $end
$var reg 1 $ RegWriteD $end
$var reg 2 % ResultSrcD [1:0] $end
$var reg 1 & MemWriteD $end
$var reg 1 ' JumpD $end
$var reg 1 ( BranchD $end
$var reg 4 ) ALUControlD [3:0] $end
$var reg 1 * ALUSrcD $end
$var reg 3 + ImmSrcD [2:0] $end
$var reg 7 , op_type $end
$var wire 10 - funct [9:0] $end
$var wire 1 . is_ALU_arith $end
$var wire 1 / is_ALU_arith_imm $end
$var wire 1 0 is_ALU_shift $end
$var wire 1 1 is_ALU_shift_imm $end
$var wire 1 2 is_ALU_logic $end
$var wire 1 3 is_ALU_logic_imm $end
$var wire 1 4 is_load $end
$var wire 1 5 is_store $end
$var wire 1 6 is_branch $end
$var wire 1 7 is_jump $end
$var wire 1 8 is_system $end
$var wire 1 9 is_lui $end
$var wire 1 : is_auipc $end
$var wire 1 ; is_fence $end
$var wire 1 < sel_arith_logic $end
$var reg 3 = alu_ctl [2:0] $end
$var reg 3 > imm_ctl [2:0] $end
$upscope $end
$upscope $end
$enddefinitions $end

#0
$dumpvars
bx !
bx "
bx #
x$
bx %
x&
x'
x(
bx000 )
x*
b0 +
bx ,
bx -
x.
x/
x0
x1
x2
x3
x4
x5
x6
x7
x8
x9
x:
x;
x<
b0 =
b0 >
$end

#6
b110011 !
b0 "
b0 #
1$
b0 %
0&
0'
0(
b1001 )
0*
b110011 ,
b0 -
1.
0/
00
01
02
03
04
05
06
07
08
09
0:
0;
1<
b1 =

#13
b100000 #
b1010 )
b100000 -
b10 =

#20
b1 "
b0 #
b1 )
b10000000 -
0.
10
0<
b1 =

#27
b10 "
b11 )
b100000000 -
00
12
b11 =

#34
b11 "
b100 )
b110000000 -
b100 =

#41
b100 "
b101 )
b1000000000 -
b101 =

#48
b101 "
b10 )
b1010000000 -
10
02
b10 =

#55
b100000 #
b1100 )
b1010100000 -
1<
b100 =

#62
b110 "
b0 #
b110 )
b1100000000 -
00
12
0<
b110 =

#69
b111 "
b111 )
b1110000000 -
b111 =

#76
b10011 !
b0 "
b1001 )
1*
b1 +
b10011 ,
b0 -
1/
02
1<
b1 =
b1 >

#83
b10 "
b11 )
b100000000 -
0/
13
0<
b11 =

#90
b11 "
b100 )
b110000000 -
b100 =

#97
b100 "
b101 )
b1000000000 -
b101 =

#104
b110 "
b110 )
b1100000000 -
b110 =

#111
b111 "
b111 )
b1110000000 -
b111 =

#118
b1 "
b1 )
b10000000 -
11
03
b1 =

#125
b101 "
b10 )
b1010000000 -
b10 =

#132
b100000 #
b1100 )
b1010100000 -
1<
b100 =

#139
b11 !
b0 "
b0 #
b1 %
b1001 )
b11 ,
b0 -
0/
01
14
b1 =
b1 >

#146
b1 "
b10000000 -
b1 =

#153
b10 "
b100000000 -
b1 =

#160
b100 "
b1000000000 -
b1 =

#167
b101 "
b1010000000 -
b1 =

#174
b100011 !
b0 "
0$
b11 %
1&
b10 +
b100011 ,
b0 -
04
15
b1 =
b10 >

#181
b1 "
b10000000 -
b1 =

#188
b10 "
b100000000 -
b1 =

#195
b1100111 !
b0 "
1$
b10 %
0&
1'
0*
b1 +
b1100111 ,
b0 -
05
17
b1 =
b1 >

#202
b1100011 !
0$
b11 %
0'
1(
b11 +
b1100011 ,
16
07
b1 =
b11 >

#209
b1 "
b10000000 -
b1 =

#216
b100 "
b1000000000 -
b1 =

#223
b101 "
b1010000000 -
b1 =

#230
b110 "
b1100000000 -
b1 =

#237
b111 "
b1110000000 -
b1 =

#244
b110111 !
b0 "
1$
b0 %
0(
b1 )
b100 +
b110111 ,
b0 -
06
19
0<
b1 =
b100 >

#251
b10111 !
1*
b10111 ,
09
1:
b1 =
b100 >
