dual_port_sram/TPSRAM_mine.sv
`define SIM // SIM 모드 설정 가능

module tpsram #(
    parameter int DEPTH = 8,
    parameter int WIDTH = 32,
    parameter int DEPTH_LOG = $clog2(DEPTH) 
)(
    input clk,
    input [WIDTH-1:0] wd,
    input [DEPTH_LOG-1:0] ra,
    input [DEPTH_LOG-1:0] wa,
    input we,
    input re,

    output reg [WIDTH-1:0] rd
);

    reg [WIDTH-1:0] dff[0:DEPTH-1];

    always @(posedge clk) begin
        if (we) begin
            dff[wa] <= wd;
        end

        if (re) begin
            if (we && (ra==wa)) begin
                rd <= wd;
            end else begin
                rd <= dff[ra];
            end
        end
    end


    `ifdef SIM 
        initial begin
          	rd = 0;
            for (int i=0; i<DEPTH; i++) begin   // Simulation을 위하여 Cell을 초기화시키는 과정 삽입. 합성에서는 동기화된 RST 사용은 수많은 LUT 사용을 유발할 수 있으니 주의.
                dff[i] = 'h0;
            end 
        end
    `endif
endmodule

dual_port_sram/tb_TPSRAM.sv
`timescale 1ns/1ps

module tb_tpsram;
    parameter int DEPTH = 8;
    parameter int WIDTH = 32;
    parameter int DEPTH_LOG = $clog2(DEPTH);

    reg clk;
    reg [WIDTH-1:0] wd;
    reg [DEPTH_LOG-1:0] ra;
    reg [DEPTH_LOG-1:0] wa;
    reg we;
    reg re;

    wire    [WIDTH-1:0] rd;


    initial clk = 0;
    always #5 clk = ~clk;
  
  tpsram #(.WIDTH(WIDTH), .DEPTH(DEPTH)) dut (.*);



    initial begin
      
        wd = 0;
        ra = 0;
    	wa = 0;
    	we = 0;
    	re = 0;
        #20;
		
      	
      	repeat(6) begin
          	wa = wa + 1;
          	we = 1;
          	wd = wd + 2;
          	#10;
      	end
		
      	wd = 0;
        ra = 0;
    	wa = 0;
    	we = 0;
    	re = 0;
      	
        repeat(6) begin
          	ra = ra + 1;
          	re = 1;
          	#10;
      	end

  
        #10;

        $display("Testbench Finished");
        $finish;
    end
	initial begin
  		$dumpfile("dump.vcd");
  		$dumpvars(1);
	end
endmodule

dual_port_sram/dualportproj/dualportproj.sim/sim_1/behav/xsim/dump.vcd
$date
   Mon Feb  9 11:14:26 2026
$end

$version
  2025.1.0
  $dumpfile ("dump.vcd") 
$end

$timescale
  1ps
$end

$scope module tb_tpsram $end
$var reg 1 ! clk $end
$var reg 32 " wd [31:0] $end
$var reg 3 # ra [2:0] $end
$var reg 3 $ wa [2:0] $end
$var reg 1 % we $end
$var reg 1 & re $end
$var wire 32 ' rd [31:0] $end
$upscope $end
$scope module glbl $end
$upscope $end
$enddefinitions $end

#0
$dumpvars
0!
b0 "
b0 #
b0 $
0%
0&
b0 '
$end

#5000
1!

#10000
0!

#15000
1!

#20000
0!
b10 "
b1 $
1%

#25000
1!

#30000
0!
b100 "
b10 $

#35000
1!

#40000
0!
b110 "
b11 $

#45000
1!

#50000
0!
b1000 "
b100 $

#55000
1!

#60000
0!
b1010 "
b101 $

#65000
1!

#70000
0!
b1100 "
b110 $

#75000
1!

#80000
0!
b0 "
b1 #
b0 $
0%
1&

#85000
1!
b10 '

#90000
0!
b10 #

#95000
1!
b100 '

#100000
0!
b11 #

#105000
1!
b110 '

#110000
0!
b100 #

#115000
1!
b1000 '

#120000
0!
b101 #

#125000
1!
b1010 '

#130000
0!
b110 #

#135000
1!
b1100 '

