RISCV32bit/Project_folder/ALU/ALU_stage.sv
`define FPGA
module ALU_stage(
    // input data
    input [31:0] RD1E,
    input [31:0] RD2E,

    input [31:0] PCE,
    // input [4:0] Rs1E,
    // input [4:0] Rs2E,
    input [4:0] RdE,
    input [24:0] ImmExtE,
    input [31:0] PCPlus4E,
    
    // Need Muxing
    input [31:0] ResultW,
    input [1:0] ForwardAE,
    input [1:0] ForwardBE,


    // input ctl
    input RegWriteE,
    input [1:0] ResultSrcE,
    input MemWriteE,
    input [2:0] ALUControlE,
    input ALUSrcE,
    input clk, rstn,

    // output ctl
    output reg RegWriteM,
    output reg [1:0] ResultSrcM,
    output reg MemWriteM,
    output ZeroE,
    

    // output data
    output reg [31:0] ALUResultM,
    output reg [4:0] RdM,
    output reg [31:0] PCPlus4M,
    output reg [31:0] PCTargetE,
    output reg [31:0] WriteDataM
);  
    wire [31:0] SrcAE, SrcBE, WriteDataE;

    // Muxing 관련
    in3_mux mx1(
        .data1(RD1E),
        .data2(ResultW),
        .data3(ALUResultM),
        .sel(ForwardAE),

        .out(SrcAE)
    );

    in3_mux mx2(
        .data1(RD2E),
        .data2(ResultW),
        .data3(ALUResultM),
        .sel(ForwardBE),

        .out(WriteDataE)
    );

    assign SrcBE = (ALUSrcE==1) ? ImmExtE : WriteDataE;


    // ALU 호출 관련
    wire [31:0] wire_ALUresult;

    ALU alu(
        .SrcAE(SrcAE),
        .SrcBE(SrcBE),
        .ALUControlE(ALUControlE),

        .ALUResult(wire_ALUresult),
        .ZeroE(ZeroE)
    );


    // ALU Result 관련
    always @(posedge clk or negedge rstn) begin
        if (!rstn) ALUResultM <= 0;
        else ALUResultM <= wire_ALUresult; 
    end   


    // PC Plus 관련
    always @(posedge clk or negedge rstn) begin
        if (!rstn) PCPlus4M <= 0;
        else PCPlus4M <= PCPlus4E; 
    end

    // PC Target 관련 
    always @(posedge clk or negedge rstn) begin
        if (!rstn) PCTargetE <= 0; 
        else PCTargetE <= PCE + ImmExtE;
    end
    // WriteDataM 관련
    always @(posedge clk or negedge rstn) begin
        if (!rstn) WriteDataM <= 0;
        else WriteDataM <= WriteDataE; 
    end

    // RdM 관련
    always @(posedge clk or negedge rstn) begin
        if (!rstn) RdM <= 0;
        else RdM <= RdE;     
    end

    // RegWriteM
    always @(posedge clk) begin
        RegWriteM <= RegWriteE;
    end

    // ResultSrcM
    always @(posedge clk) begin
        ResultSrcM <= ResultSrcE;
    end

    // MemWriteE
    always @(posedge clk) begin
        MemWriteM <= MemWriteE;
    end   

    `ifdef SIM
        initial begin
            RegWriteM = 0;
            ResultSrcM = 0;
            MemWriteM = 0;
            
            // output data
            ALUResultM = 0;
            RdM = 0;
            PCPlus4M = 0;
            PCTargetE = 0;
            WriteDataM = 0;
        end
    `endif


endmodule


module ALU(
    input [31:0] SrcAE,
    input [31:0] SrcBE,
    input [2:0] ALUControlE,

    output reg [31:0] ALUResult,
    output reg ZeroE
);
    localparam sADD = 1;
    localparam sSUB = 2;
    localparam sMUL = 3;
    localparam sDIV = 4;
    localparam sINC = 5;
    localparam sDEC = 6;
    localparam sNEG = 7;
    wire [31:0] ADD, SUB, MUL, DIV, INC, DEC, NEG;

    assign ADD = SrcAE + SrcBE;
    assign SUB = SrcAE - SrcBE;
    assign MUL = SrcAE * SrcBE;
    assign DIV = SrcAE / SrcBE;
    assign INC = SrcAE + 1;
    assign DEC = SrcAE - 1;
    assign NEG = ~SrcAE + 1;

    
    // Case 구문으로 입력에 맞게 선택 후 출력함.
    always @(*) begin
        case(ALUControlE)
            default : ALUResult = 0;
            sADD : ALUResult = ADD;
            sSUB : ALUResult = SUB;
            sMUL : ALUResult = MUL;
            sDIV : ALUResult = DIV;
            sINC : ALUResult = INC;
            sDEC : ALUResult = DEC;
            sNEG : ALUResult = NEG;
        endcase

        if (ALUResult==0) ZeroE = 1;
        else ZeroE = 0;
    end


    `ifdef SIM
        initial begin
            ALUResult = 0;
            ZeroE = 0;
        end
    `endif

endmodule

module in3_mux(
    input [31:0] data1,
    input [31:0] data2,
    input [31:0] data3,
    input [1:0] sel,

    output [31:0] out
);

    assign out = (sel==2'b00) ? data1 : (sel==2'b01) ? data2 : (sel==2'b10) ? data3 : 'hz;
endmodule

RISCV32bit/Project_folder/ALU/tb_ALU_stage.sv
module tb_ALU_stage;

    // I/O Setting
    // logic [31:0] RD1E;
    // logic [31:0] RD2E;

    // logic [31:0] PCE;

    // logic [24:0] ImmExtE;
    // logic [31:0] PCPlus4E;
    
    // // Need Muxing
    // logic [31:0] ResultW;
    // logic [1:0] ForwardAE;
    // logic [1:0] ForwardBE;

    // logic RegWriteE;
    // logic [1:0] ResultSrcE;
    // logic MemWriteE;
    // logic [2:0] ALUControlE;
    // logic ALUSrcE;

    logic clk;
    logic rstn;


    logic RegWriteM;
    logic [1:0] ResultSrcM;
    logic MemWriteM;
    logic ZeroE;
    
    logic [31:0] ALUResultM;
    logic [4:0] RdM;
    logic [31:0] PCPlus4M;
    logic [31:0] PCTargetE;
    logic [31:0] WriteDataM;


    


    initial clk = 0;
    always #3 clk = ~clk;

    // ALUControlE로 연산 종류 설정
    // RD1E, RD2E로 값 대입
    // ForwardAE, ForwardBE로 MUX 조절 가능

    typedef struct packed{
        logic [31:0] RD1E;
        logic [31:0] RD2E;

        logic [31:0] PCE;

        logic [24:0] ImmExtE;
        logic [31:0] PCPlus4E;
        
        // Need Muxing
        logic [31:0] ResultW;
        logic [1:0] ForwardAE;
        logic [1:0] ForwardBE;

        logic RegWriteE;
        logic [1:0] ResultSrcE;
        logic MemWriteE;
        logic [2:0] ALUControlE;
        logic ALUSrcE;
        logic [4:0] RdE;

    } input_ports;


    // 2. ALU 제어 신호 파라미터 정의
    localparam logic [2:0] IDLE = 3'b000;
    localparam logic [2:0] sADD = 3'b001;
    localparam logic [2:0] sSUB = 3'b010;
    localparam logic [2:0] sMUL = 3'b011;
    localparam logic [2:0] sDIV = 3'b100;
    localparam logic [2:0] sINC = 3'b101;
    localparam logic [2:0] sDEC = 3'b110;
    localparam logic [2:0] sNEG = 3'b111;

    localparam logic [1:0] FWD_REG = 2'b00; // 기본 레지스터 값 사용
    localparam logic [1:0] FWD_WB  = 2'b01; // Writeback 단계에서 포워딩
    localparam logic [1:0] FWD_MEM = 2'b10; // Memory 단계에서 포워딩



    input_ports test_vectors [8] = '{

        // [index -1] init
        '{RD1E: 32'd0, RD2E: 32'd0, PCE: 32'h00, ImmExtE: 25'd0, PCPlus4E: 32'h000,
          ResultW: 32'd0, ForwardAE: FWD_REG, ForwardBE: FWD_REG,
          RegWriteE: 1'b0, ResultSrcE: 2'b00, MemWriteE: 1'b0, ALUControlE: 0, ALUSrcE: 1'b0, RdE : 5'd0},
        
        // [Index 0] 일반적인 더하기 (sADD)
        // SrcA = RD1E(10), SrcB = RD2E(20) -> 예상 결과: 30
        '{RD1E: 32'd10, RD2E: 32'd20, PCE: 32'h100, ImmExtE: 25'd0, PCPlus4E: 32'h104,
          ResultW: 32'd0, ForwardAE: FWD_REG, ForwardBE: FWD_REG,
          RegWriteE: 1'b1, ResultSrcE: 2'b00, MemWriteE: 1'b0, ALUControlE: sADD, ALUSrcE: 1'b0, RdE : 5'd1},

        // [Index 1] 포워딩을 동반한 빼기 (sSUB)
        // SrcA = RD1E(50), SrcB = ResultW(15) (ForwardB 사용) -> 예상 결과: 50 - 15 = 35
        '{RD1E: 32'd50, RD2E: 32'd0, PCE: 32'h104, ImmExtE: 25'd0, PCPlus4E: 32'h108,
          ResultW: 32'd15, ForwardAE: FWD_REG, ForwardBE: FWD_WB,
          RegWriteE: 1'b1, ResultSrcE: 2'b00, MemWriteE: 1'b0, ALUControlE: sSUB, ALUSrcE: 1'b0, RdE : 5'd2},

        // [Index 2] 즉치값을 이용한 곱하기 (sMUL)
        // SrcA = RD1E(5), SrcB = ImmExtE(4) (ALUSrcE=1) -> 예상 결과: 5 * 4 = 20
        '{RD1E: 32'd5, RD2E: 32'd99, PCE: 32'h108, ImmExtE: 25'd4, PCPlus4E: 32'h10C,
          ResultW: 32'd0, ForwardAE: FWD_REG, ForwardBE: FWD_REG,
          RegWriteE: 1'b1, ResultSrcE: 2'b00, MemWriteE: 1'b0, ALUControlE: sMUL, ALUSrcE: 1'b1, RdE : 5'd3},

        // [Index 3] 양방향 포워딩을 동반한 나누기 (sDIV)
        // SrcA = ResultW(100), SrcB = ResultW(20) (둘 다 WB에서 포워딩) -> 예상 결과: 100 / 100 = 1
        '{RD1E: 32'd0, RD2E: 32'd0, PCE: 32'h10C, ImmExtE: 25'd0, PCPlus4E: 32'h110,
          ResultW: 32'd100, ForwardAE: FWD_WB, ForwardBE: FWD_WB, // 둘 다 ResultW 값을 가져옴 (편의상 동일값)
          RegWriteE: 1'b1, ResultSrcE: 2'b00, MemWriteE: 1'b0, ALUControlE: sDIV, ALUSrcE: 1'b0, RdE : 5'd4},

        // [Index 4] 값 증가 (sINC) 
        // SrcA = RD1E(99) -> 예상 결과: 100 (ALU 내부에서 +1 처리한다고 가정)
        '{RD1E: 32'd99, RD2E: 32'd0, PCE: 32'h110, ImmExtE: 25'd0, PCPlus4E: 32'h114,
          ResultW: 32'd0, ForwardAE: FWD_REG, ForwardBE: FWD_REG,
          RegWriteE: 1'b1, ResultSrcE: 2'b00, MemWriteE: 1'b0, ALUControlE: sINC, ALUSrcE: 1'b0, RdE : 5'd5},

        // [Index 5] 포워딩 값을 감소 (sDEC)
        // SrcA = ResultW(8) (ForwardA 사용) -> 예상 결과: 7 (ALU 내부에서 -1 처리한다고 가정)
        '{RD1E: 32'd0, RD2E: 32'd0, PCE: 32'h114, ImmExtE: 25'd0, PCPlus4E: 32'h118,
          ResultW: 32'd8, ForwardAE: FWD_WB, ForwardBE: FWD_REG,
          RegWriteE: 1'b1, ResultSrcE: 2'b00, MemWriteE: 1'b0, ALUControlE: sDEC, ALUSrcE: 1'b0, RdE : 5'd6},

        // [Index 6] 2의 보수 부호 반전 (sNEG)
        // SrcA = RD1E(5) -> 예상 결과: -5 (32'hFFFFFFFB)
        '{RD1E: 32'd5, RD2E: 32'd0, PCE: 32'h118, ImmExtE: 25'd0, PCPlus4E: 32'h11C,
          ResultW: 32'd0, ForwardAE: FWD_REG, ForwardBE: FWD_REG,
          RegWriteE: 1'b1, ResultSrcE: 2'b00, MemWriteE: 1'b0, ALUControlE: sNEG, ALUSrcE: 1'b0, RdE : 5'd7}
    };

    input_ports tb_stimulus;

    ALU_stage dut(
        .RD1E(tb_stimulus.RD1E),
        .RD2E(tb_stimulus.RD2E),
        .PCE(tb_stimulus.PCE),

        .ImmExtE(tb_stimulus.ImmExtE),
        .PCPlus4E(tb_stimulus.PCPlus4E),
        
        // Need Muxing
        .ResultW(tb_stimulus.ResultW),
        .ForwardAE(tb_stimulus.ForwardAE),
        .ForwardBE(tb_stimulus.ForwardBE),

        .RegWriteE(tb_stimulus.RegWriteE),
        .ResultSrcE(tb_stimulus.ResultSrcE),
        .MemWriteE(tb_stimulus.MemWriteE),
        .ALUControlE(tb_stimulus.ALUControlE),
        .ALUSrcE(tb_stimulus.ALUSrcE),
        .RdE(tb_stimulus.RdE),

        // 여기서부터 상위 모듈의 I/O 직결
        // clk rstn
        .clk(clk),
        .rstn(rstn),

        // outputs
        .RegWriteM(RegWriteM),
        .ResultSrcM(ResultSrcM),
        .MemWriteM(MemWriteM),
        .ZeroE(ZeroE),
            
        .ALUResultM(ALUResultM),
        .RdM(RdM),
        .PCPlus4M(PCPlus4M),
        .PCTargetE(PCTargetE),
        .WriteDataM(WriteDataM)


    );

    reg [3:0] cnt;

    // TB 작성
    initial begin
        rstn <= 0;
        tb_stimulus <= 0;
        cnt <= 0;
        repeat(2) @(posedge clk);
        rstn <= 1;
        repeat(2) @(posedge clk);

        foreach (test_vectors[i]) begin
            tb_stimulus <= test_vectors[i];
            @(posedge clk);
        end

        repeat(5) @(posedge clk);
        $finish;
    end

    initial begin
        wait(rstn);
        repeat(4) @(posedge clk);


        for (int i=0; i<8; i++) begin
            input_ports check_vaild = test_vectors[i];

            case(check_vaild.ALUControlE)
                    1 : begin
                        if (ALUResultM==(check_vaild.RD1E+check_vaild.RD2E)) $display("Injecting Case : ADD, Pass");    
                        else begin
                            $display("Injecting Case : ADD, Error : %5d", ALUResultM);
                            cnt <= cnt+1;
                        end
                    end
                    2 : begin
                        if (ALUResultM==(check_vaild.RD1E-check_vaild.ResultW)) $display("Injecting Case : sSUB, Pass");
                        else begin
                            $display("Injecting Case : sSUB, Error : %5d", ALUResultM);
                            cnt <= cnt+1;
                        end
                    end
                    3 : begin
                        if (ALUResultM==(check_vaild.RD1E*check_vaild.ImmExtE)) $display("Injecting Case : sMUL, Pass");
                        else begin
                            $display("Injecting Case : sMUL, Error : %5d", ALUResultM);
                            cnt <= cnt+1;
                        end
                    end
                    4 : begin
                        if (ALUResultM==1'b1) $display("Injecting Case : sDIV, Pass");
                        else begin
                            $display("Injecting Case : sDIV, Error : %5d", ALUResultM);
                            cnt <= cnt+1;
                        end
                    end
                    5 : begin
                        if (ALUResultM==(check_vaild.RD1E+1)) $display("Injecting Case : sINC, Pass");
                        else begin
                            $display("Injecting Case : sINC, Error : %5d", ALUResultM);
                            cnt <= cnt+1;
                        end
                    end
                    6 : begin
                        if (ALUResultM==(check_vaild.ResultW-1)) $display("Injecting Case : sDEC, Pass");
                        else begin
                            $display("Injecting Case : sDEC, Error : %5d", ALUResultM);
                            cnt <= cnt+1;
                        end
                    end
                    7 : begin
                        if (ALUResultM==(~check_vaild.RD1E+1)) $display("Injecting Case : sNEG, Pass");
                        else begin
                            $display("Injecting Case : sNEG, Error : %5d", ALUResultM);
                            cnt <= cnt+1;
                        end
                    end

                    0 : $display("Initializing...");
            endcase
            @(posedge clk);
        end

        $display("Exiting...");
    end


    // Waveform Settings
    initial begin
        $dumpfile("ALUstage_Simulation_Waveform.vcd");
        $dumpvars(0, dut);
    end




endmodule

RISCV32bit/Project_folder/ALU/simulation_ALUstage/simulation_ALUstage.sim/sim_1/behav/xsim/ALUstage_Simulation_Waveform.vcd
$date
   Wed Apr  1 06:29:32 2026
$end

$version
  2025.1.0
  $dumpfile ("ALUstage_Simulation_Waveform.vcd") 
$end

$timescale
  1ps
$end

$scope module tb_ALU_stage $end
$scope module dut $end
$var wire 32 ! RD1E [31:0] $end
$var wire 32 " RD2E [31:0] $end
$var wire 32 # PCE [31:0] $end
$var wire 5 $ RdE [4:0] $end
$var wire 25 % ImmExtE [24:0] $end
$var wire 32 & PCPlus4E [31:0] $end
$var wire 32 ' ResultW [31:0] $end
$var wire 2 ( ForwardAE [1:0] $end
$var wire 2 ) ForwardBE [1:0] $end
$var wire 1 * RegWriteE $end
$var wire 2 + ResultSrcE [1:0] $end
$var wire 1 , MemWriteE $end
$var wire 3 - ALUControlE [2:0] $end
$var wire 1 . ALUSrcE $end
$var wire 1 / clk $end
$var wire 1 0 rstn $end
$var reg 1 1 RegWriteM $end
$var reg 2 2 ResultSrcM [1:0] $end
$var reg 1 3 MemWriteM $end
$var wire 1 4 ZeroE $end
$var reg 32 5 ALUResultM [31:0] $end
$var reg 5 6 RdM [4:0] $end
$var reg 32 7 PCPlus4M [31:0] $end
$var reg 32 8 PCTargetE [31:0] $end
$var reg 32 9 WriteDataM [31:0] $end
$var wire 32 : SrcAE [31:0] $end
$var wire 32 ; SrcBE [31:0] $end
$var wire 32 < WriteDataE [31:0] $end
$var wire 32 = wire_ALUresult [31:0] $end
$scope module mx1 $end
$var wire 32 ! data1 [31:0] $end
$var wire 32 ' data2 [31:0] $end
$var wire 32 5 data3 [31:0] $end
$var wire 2 ( sel [1:0] $end
$var wire 32 : out [31:0] $end
$upscope $end
$scope module mx2 $end
$var wire 32 " data1 [31:0] $end
$var wire 32 ' data2 [31:0] $end
$var wire 32 5 data3 [31:0] $end
$var wire 2 ) sel [1:0] $end
$var wire 32 < out [31:0] $end
$upscope $end
$scope module alu $end
$var wire 32 : SrcAE [31:0] $end
$var wire 32 ; SrcBE [31:0] $end
$var wire 3 - ALUControlE [2:0] $end
$var reg 32 > ALUResult [31:0] $end
$var reg 1 ? ZeroE $end
$var wire 32 @ ADD [31:0] $end
$var wire 32 A SUB [31:0] $end
$var wire 32 B MUL [31:0] $end
$var wire 32 C DIV [31:0] $end
$var wire 32 D INC [31:0] $end
$var wire 32 E DEC [31:0] $end
$var wire 32 F NEG [31:0] $end
$upscope $end
$upscope $end
$upscope $end
$enddefinitions $end

#0
$dumpvars
b0 !
b0 "
b0 #
b0 $
b0 %
b0 &
b0 '
b0 (
b0 )
0*
b0 +
0,
b0 -
0.
0/
00
01
b0 2
03
14
b0 5
b0 6
b0 7
b0 8
b0 9
b0 :
b0 ;
b0 <
b0 =
b0 >
1?
b0 @
b0 A
b0 B
bx C
b1 D
b11111111111111111111111111111111 E
b0 F
$end

#3000
1/

#6000
0/

#9000
1/
10

#12000
0/

#15000
1/

#18000
0/

#21000
1/

#24000
0/

#27000
b1010 !
b10100 "
b100000000 #
b1 $
b100000100 &
1*
b1 -
1/
04
b1010 :
b10100 ;
b10100 <
b11110 =
b11110 >
0?
b11110 @
b11111111111111111111111111110110 A
b11001000 B
b0 C
b1011 D
b1001 E
b11111111111111111111111111110110 F

#30000
0/

#33000
b110010 !
b0 "
b100000100 #
b10 $
b100001000 &
b1111 '
b1 )
b10 -
1/
11
b11110 5
b1 6
b100000100 7
b100000000 8
b10100 9
b110010 :
b1111 ;
b1111 <
b100011 =
b100011 >
b1000001 @
b100011 A
b1011101110 B
b11 C
b110011 D
b110001 E
b11111111111111111111111111001110 F

#36000
0/

#39000
b101 !
b1100011 "
b100001000 #
b11 $
b100 %
b100001100 &
b0 '
b0 )
b11 -
1.
1/
b100011 5
b10 6
b100001000 7
b100000100 8
b1111 9
b101 :
b100 ;
b1100011 <
b10100 =
b10100 >
b1001 @
b1 A
b10100 B
b1 C
b110 D
b100 E
b11111111111111111111111111111011 F

#42000
0/

#45000
b0 !
b0 "
b100001100 #
b100 $
b0 %
b100010000 &
b1100100 '
b1 (
b1 )
b100 -
0.
1/
b10100 5
b11 6
b100001100 7
b100001100 8
b1100011 9
b1100100 :
b1100100 ;
b1100100 <
b1 =
b1 >
b11001000 @
b0 A
b10011100010000 B
b1100101 D
b1100011 E
b11111111111111111111111110011100 F

#48000
0/

#51000
b1100011 !
b100010000 #
b101 $
b100010100 &
b0 '
b0 (
b0 )
b101 -
1/
b1 5
b100 6
b100010000 7
b1100100 9
b1100011 :
b0 ;
b0 <
b1100100 =
b1100100 >
b1100011 @
b1100011 A
b0 B
bx C
b1100100 D
b1100010 E
b11111111111111111111111110011101 F

#54000
0/

#57000
b0 !
b100010100 #
b110 $
b100011000 &
b1000 '
b1 (
b110 -
1/
b1100100 5
b101 6
b100010100 7
b100010000 8
b0 9
b1000 :
b111 =
b111 >
b1000 @
b1000 A
b1001 D
b111 E
b11111111111111111111111111111000 F

#60000
0/

#63000
b101 !
b100011000 #
b111 $
b100011100 &
b0 '
b0 (
b111 -
1/
b111 5
b110 6
b100011000 7
b100010100 8
b101 :
b11111111111111111111111111111011 =
b11111111111111111111111111111011 >
b101 @
b101 A
b110 D
b100 E
b11111111111111111111111111111011 F

#66000
0/

#69000
1/
b11111111111111111111111111111011 5
b111 6
b100011100 7
b100011000 8

