dual_port_sram/DPSRAM_mine.sv
// Code your design here
`define FPGA // SIM or Anything else.

module dpsram #(
    parameter int DEPTH = 8,
    parameter int WIDTH = 32,
    parameter int DEPTH_LOG = $clog2(DEPTH) 
)(
    // input 
    input   [WIDTH-1:0]     din_a, 
    input   [DEPTH_LOG-1:0]addr_a, 
    input                    we_a,
    input                    cs_a, 

    input                     clk,

    input   [DEPTH_LOG-1:0]addr_b, 
    input   [WIDTH-1:0]     din_b, 
    input                    we_b,
    input                    cs_b, 
    
    // output
    output reg [WIDTH-1:0]    dout_a,
    output reg [WIDTH-1:0]    dout_b
);

    reg [WIDTH-1:0] dff[0:DEPTH-1];
    wire [1:0]  we;
    assign we = {we_a, we_b};

    wire addr_match = (addr_a == addr_b);

    always @(posedge clk) begin // WRITE      
        if (cs_a&&we_a) begin 
            dff[addr_a] <= din_a;
        end
        if (cs_b&&we_b)   begin  // Priority 설정 : Port A에 우선권 부여
            if (!addr_match||!(cs_a&&we_a))    dff[addr_b] <= din_b;      
        end
    end
    

    always @(posedge clk) begin // READ
        if ((cs_a&&cs_b)&&addr_match) begin
            case(we)
                2'd0 : begin
                    dout_a <= dff[addr_a];
                    dout_b <= dff[addr_b];
                end

                2'd1 :     dout_a <= din_b;
                2'd2 :     dout_b <= din_a;
                default : ;

            endcase

        end


        else begin
            if (cs_a&&!we_a)  dout_a <= dff[addr_a]; 
            if (cs_b&&!we_b)  dout_b <= dff[addr_b];
        end
    end



    `ifdef SIM 
        initial begin
          	dout_a = 0;
          	dout_b = 0;
            for (int i=0; i<DEPTH; i++) begin   // Simulation을 위하여 Cell을 초기화시키는 과정 삽입. 합성에서는 동기화된 RST 사용은 수많은 LUT 사용을 유발할 수 있으니 주의.
                dff[i] = 'h0;
            end 
        end
    `endif
endmodule

dual_port_sram/tb_DPSRAM.sv
// Code your testbench here
// or browse Examples
`timescale 1ns/1ps

module tb_dpsram;

    parameter int DEPTH = 8;
    parameter int WIDTH = 32;
    parameter int DEPTH_LOG = $clog2(DEPTH); 

    // reg 
    reg   [WIDTH-1:0]     din_a; 
    reg   [DEPTH_LOG-1:0]addr_a; 
    reg                    we_a;
    reg                    cs_a; 

    reg                     clk;

    reg   [DEPTH_LOG-1:0]addr_b; 
    reg   [WIDTH-1:0]     din_b; 
    reg                    we_b;
    reg                    cs_b; 
    
    // wire
    wire  [WIDTH-1:0]    dout_a;
    wire  [WIDTH-1:0]    dout_b;

  dpsram #(DEPTH, WIDTH) dpsram_cell(.*);  
    
    initial clk = 0;
    always #3 clk = ~clk;

    
    initial begin
        din_a = 1; 
        addr_a = 0; 
        we_a = 0;
        cs_a = 0; 

        addr_b = 0; 
        din_b = 3; 
        we_b = 0;
        cs_b = 0; 


        #18;
        we_a = 1;
        we_b = 1;
        cs_a = 1;
        cs_b = 1;

        // 같은 주소에 Writing 하는 것 Test
        for (int i=0; i<8; i++) begin
            din_a = din_a + i;
            din_b = din_b + i;

            addr_a = i;
            addr_b = i;

            @(posedge clk);        
        end

        $display("Writing Test Passed");
        // 동시 출력 test
        #15;

        we_a = 0;
        we_b = 0;
        for (int i=0; i<4; i++) begin

            addr_a = i;
            addr_b = i+4;

            @(posedge clk);        
        end
        $display("Reading Test Passed");
        #30;
        
        $display("Feed Forward (Bypass) Test Start");
        // 포트 A는 쓰고, 포트 B는 동일 주소를 읽는 상황
        addr_a = 4; din_a = 32'hFEED_BEEF; we_a = 1; cs_a = 1;
        addr_b = 4; we_b = 0; cs_b = 1; // 동일 주소 4번
        
        @(posedge clk);
        #1; 
        if (dout_b == 32'hFEED_BEEF) 
            $display("SUCCESS: Port A data forwarded to Port B!");
        else 
            $display("FAIL: Port B read old data or X");
        
        // 포트 B는 쓰고, 포트 A는 동일 주소를 읽는 상황
        we_a = 0; we_b = 1; din_b = 32'hAAAA_BBBB;
        @(posedge clk);
        #1;
        if (dout_a == 32'hAAAA_BBBB)
            $display("SUCCESS: Port B data forwarded to Port A!");
        $finish;

    end

    

	initial begin
  		$dumpfile("dump.vcd");
  		$dumpvars(1);
	end
endmodule

dual_port_sram/dualportproj2/dualportproj2.sim/sim_1/behav/xsim/dump.vcd
$date
   Tue Feb 10 11:24:41 2026
$end

$version
  2025.1.0
  $dumpfile ("dump.vcd") 
$end

$timescale
  1ps
$end

$scope module tb_dpsram $end
$var reg 32 ! din_a [31:0] $end
$var reg 3 " addr_a [2:0] $end
$var reg 1 # we_a $end
$var reg 1 $ cs_a $end
$var reg 1 % clk $end
$var reg 3 & addr_b [2:0] $end
$var reg 32 ' din_b [31:0] $end
$var reg 1 ( we_b $end
$var reg 1 ) cs_b $end
$var wire 32 * dout_a [31:0] $end
$var wire 32 + dout_b [31:0] $end
$upscope $end
$scope module glbl $end
$upscope $end
$enddefinitions $end

#0
$dumpvars
b1 !
b0 "
0#
0$
0%
b0 &
b11 '
0(
0)
b0 *
b0 +
$end

#3000
1%

#6000
0%

#9000
1%

#12000
0%

#15000
1%

#18000
1#
1$
0%
1(
1)

#21000
b10 !
b1 "
1%
b1 &
b100 '

#24000
0%

#27000
b100 !
b10 "
1%
b10 &
b110 '

#30000
0%

#33000
b111 !
b11 "
1%
b11 &
b1001 '

#36000
0%

#39000
b1011 !
b100 "
1%
b100 &
b1101 '

#42000
0%

#45000
b10000 !
b101 "
1%
b101 &
b10010 '

#48000
0%

#51000
b10110 !
b110 "
1%
b110 &
b11000 '

#54000
0%

#57000
b11101 !
b111 "
1%
b111 &
b11111 '

#60000
0%

#63000
1%

#66000
0%

#69000
1%

#72000
0%

#75000
1%

#78000
b0 "
0#
0%
b100 &
0(

#81000
b1 "
1%
b101 &
b10 *
b10000 +

#84000
0%

#87000
b10 "
1%
b110 &
b100 *
b10110 +

#90000
0%

#93000
b11 "
1%
b111 &
b111 *
b11101 +

#96000
0%

#99000
1%

#102000
0%

#105000
1%

#108000
0%

#111000
1%

#114000
0%

#117000
1%

#120000
0%

#123000
1%

#126000
0%

#129000
1%

#132000
0%

#135000
1%

#138000
0%

#141000
1%

#144000
b11111110111011011011111011101111 !
b100 "
1#
0%
b100 &

#147000
1%
b11111110111011011011111011101111 +

#148000
0#
b10101010101010101011101110111011 '
1(

#150000
0%

#153000
1%
b10101010101010101011101110111011 *
