RISCV32bit/Project_folder/Extend/inst_extend.sv
`define FPGA
module inst_extend(
  input [24:0] inst,
  input [2:0] ImmSrcD,  // 이 부분은 수정

  output [31:0] ImmExtD  
);  
    // State 선언
    localparam int IDLE = 0;
    localparam int I_type = 1;
    localparam int S_type = 2;
    localparam int B_type = 3;
    localparam int U_type = 4;
    localparam int J_type = 5;
    localparam int UNKNOWN = 6;

    // output을 위한 reg/wire 설정
    reg [31:0] mem;
    assign ImmExtD = mem;

    // S type
    wire [6:0] s_ins1; 
    wire [4:0] s_ins2;

    assign s_ins1 = inst[24:18];    // 7bits
    assign s_ins2 = inst[4:0];      // 5bits

    // B type
    wire [12:0] b_inst;
    assign b_inst = {inst[24], inst[0], inst[23:18], inst[4:1], 1'b0};

    // J type 
    wire [20:0] j_inst;
    assign j_inst = {inst[24], inst[12:5], inst[13], inst[23:14], 1'b0};


    // 올바른 값을 mem에 할당
    always @(*) begin
        case(ImmSrcD)
            IDLE : mem = {{7{1'b0}}, inst}; 
            // addi, lw
            I_type : mem = {{7{inst[24]}}, inst}; 
            S_type : mem = {{20{inst[24]}}, s_ins1, s_ins2}; 
            B_type : mem = {{19{inst[24]}}, b_inst};
            U_type : mem = {inst[24:5], {12{1'b0}}};
            J_type : mem = {{11{inst[24]}}, j_inst};
            UNKNOWN : mem = 0;
            default : mem = 'hzzzz;
        endcase
    end

    `ifdef SIM
        initial mem = 0;
    `endif


endmodule

RISCV32bit/Project_folder/Extend/tb_inst_extend.sv
module tb_inst_extend;
    // logic [24:0] inst;
    // logic [2:0] ImmSrcD;  // 이 부분은 수정

    logic [31:0] ImmExtD;


    // State 선언
    localparam int IDLE = 0;
    localparam int I_type = 1;
    localparam int S_type = 2;
    localparam int B_type = 3;
    localparam int U_type = 4;
    localparam int J_type = 5;
    localparam int UNKNOWN = 6;


    typedef struct packed {
        logic [24:0] inst;
        logic [2:0] ImmSrcD;
    }  i_ports;

    i_ports case_lists[7] = '{
        '{inst : 25'h1234567, ImmSrcD : 0}, // IDLE
        '{inst : 25'h1234321, ImmSrcD : 1}, // I_type        
        '{inst : 25'h0123321, ImmSrcD : 2}, // S_type 
        '{inst : 25'h0301113, ImmSrcD : 3}, // B_type 
        '{inst : 25'h0202231, ImmSrcD : 4}, // U_type 0001 0000 0001 0001 0001 0000 0000 0000
        '{inst : 25'h1209209, ImmSrcD : 5}, // J_type 
        '{inst : 25'h1123123, ImmSrcD : 6}  // UNKNOWN
    };
    
    i_ports input_cases;

    inst_extend dut(
        // input
        .inst(input_cases.inst),
        .ImmSrcD(input_cases.ImmSrcD),
        // output
        .ImmExtD(ImmExtD)
    );


    initial begin
        #3;

        foreach (case_lists[i]) begin
            input_cases = case_lists[i];
            $display("State : %0d", i);
            #3;
            case(i)
                IDLE : begin
                    if (ImmExtD==32'h01234567) $display("Passed IDLE State");
                    else $display("Failed IDLE State, %0h", ImmExtD);
                end
                I_type : begin
                    if (ImmExtD==32'hFF234321) $display("Passed I TYPE State");
                    else $display("Failed I TYPE State, %0h", ImmExtD);
                end
                S_type : begin
                    if (ImmExtD==32'h00000081) $display("Passed S TYPE State");
                    else $display("Failed S TYPE State, %0h", ImmExtD);
                end
                B_type : begin
                    if (ImmExtD==32'h00000992) $display("Passed B TYPE State");
                    else $display("Failed B TYPE State, %0h", ImmExtD);
                end
                U_type : begin
                    if (ImmExtD==32'h10111000) $display("Passed U TYPE State");
                    else $display("Failed U TYPE State, %0h", ImmExtD);
                end
                J_type : begin
                    if (ImmExtD==32'hFFF90104) $display("Passed J TYPE State");
                    else $display("Failed J TYPE State, %0h", ImmExtD);
                end
                UNKNOWN : begin
                    if (ImmExtD==32'h00000000) $display("Passed UNKNOWN TYPE State");
                    else $display("Failed UNKNOWN TYPE State, %0h", ImmExtD);
                end
                default : begin
                    if (ImmExtD==32'hzzzz_zzzz) $display("Passed Default State");
                    else $display("Failed Default TYPE State, %0h", ImmExtD);
                end 
            endcase
            #1;
        end
        #2;
        $finish;
    end


    initial begin
        $dumpfile("inst_extend_waveform.vcd");
        $dumpvars(0, dut);
    end

endmodule

RISCV32bit/Project_folder/Extend/inst_extended_vivado/inst_extended_vivado.sim/sim_1/behav/xsim/inst_extend_waveform.vcd
$date
   Thu Apr  2 05:29:33 2026
$end

$version
  2025.1.0
  $dumpfile ("inst_extend_waveform.vcd") 
$end

$timescale
  1ps
$end

$scope module tb_inst_extend $end
$scope module dut $end
$var wire 25 ! inst [24:0] $end
$var wire 3 " ImmSrcD [2:0] $end
$var wire 32 # ImmExtD [31:0] $end
$var reg 32 $ mem [31:0] $end
$var wire 7 % s_ins1 [6:0] $end
$var wire 5 & s_ins2 [4:0] $end
$var wire 13 ' b_inst [12:0] $end
$var wire 21 ( j_inst [20:0] $end
$upscope $end
$upscope $end
$enddefinitions $end

#0
$dumpvars
bx !
bx "
bz #
bz $
bx %
bx &
bx0 '
bx0 (
$end

#3000
b1001000110100010101100111 !
b0 "
b1001000110100010101100111 #
b1001000110100010101100111 $
b1001000 %
b111 &
b1100100000110 '
b100101011000100011010 (

#7000
b1001000110100001100100001 !
b1 "
b11111111001000110100001100100001 #
b11111111001000110100001100100001 $
b1 &
b1100100000000 '
b100011001000100011010 (

#11000
b100100011001100100001 !
b10 "
b10000001 #
b10000001 $
b100 %
b100010000000 '
b10011001100010010000 (

#15000
b1100000001000100010011 !
b11 "
b100110010010 #
b100110010010 $
b1100 %
b10011 &
b100110010010 '
b10001000000110000000 (

#19000
b1000000010001000110001 !
b100 "
b10000000100010001000000000000 #
b10000000100010001000000000000 $
b1000 %
b10001 &
b100100010000 '
b10001100100000000 (

#23000
b1001000001001001000001001 !
b101 "
b11111111111110010000000100000100 #
b11111111111110010000000100000100 $
b1001000 %
b1001 &
b1100100001000 '
b110010000000100000100 (

#27000
b1000100100011000100100011 !
b110 "
b0 #
b0 $
b1000100 %
b11 &
b1100010000010 '
b110001001100010010000 (
