RISCV32bit/Project_folder/Extend/inst_extend.sv
`define SIM
module inst_extend(
  input [31:0] inst,
  input [2:0] ImmSrcD,  // 이 부분은 수정

  output [31:0] ImmExtD  
);  
    // State 선언
    localparam int IDLE = 0;
    localparam int I_type = 1;
    localparam int S_type = 2;
    localparam int B_type = 3;
    localparam int U_type = 4;
    localparam int J_type = 5;
    localparam int UNKNOWN = 6;

    reg [31:0] mem;
    assign ImmExtD = mem;

    always @(*) begin
        case(ImmSrcD)
            IDLE : mem = 32'b0; 
            
            // 💡 I-type (addi, lw 등)
            I_type : mem = {{20{inst[31]}}, inst[31:20]}; 
            
            // 💡 S-type (sw)
            S_type : mem = {{20{inst[31]}}, inst[31:25], inst[11:7]}; 
            
            // 💡 B-type (beq 등)
            B_type : mem = {{20{inst[31]}}, inst[7], inst[30:25], inst[11:8], 1'b0};
            
            // 💡 U-type (lui 등)
            U_type : mem = {inst[31:12], 12'b0};
            
            // 💡 J-type (jal)
            J_type : mem = {{12{inst[31]}}, inst[19:12], inst[20], inst[30:21], 1'b0};
            
            UNKNOWN : mem = 32'b0;
            default : mem = 32'b0;
        endcase
    end

    `ifdef SIM
        initial mem = 0;
    `endif

endmodule

RISCV32bit/Project_folder/Extend/tb_inst_extend.sv
module tb_inst_extend;
    // logic [24:0] inst;
    // logic [2:0] ImmSrcD;  // 이 부분은 수정

    logic [31:0] ImmExtD;


    // State 선언
    localparam int IDLE = 0;
    localparam int I_type = 1;
    localparam int S_type = 2;
    localparam int B_type = 3;
    localparam int U_type = 4;
    localparam int J_type = 5;
    localparam int UNKNOWN = 6;


    typedef struct packed {
        logic [31:0] inst;
        logic [2:0] ImmSrcD;
    }  i_ports;

    i_ports case_lists[7] = '{
        '{inst : 32'h01234567, ImmSrcD : 0}, // IDLE    [FIXED]
        '{inst : 32'h01234321, ImmSrcD : 1}, // I_type  [FIXED]
        '{inst : 32'h00123321, ImmSrcD : 2}, // S_type  [FIXED]
        '{inst : 32'h00301113, ImmSrcD : 3}, // B_type  [FIXED]
        '{inst : 32'h00202231, ImmSrcD : 4}, // U_type  [FIXED]
        '{inst : 32'h01209209, ImmSrcD : 5}, // J_type  [FIXED]
        '{inst : 32'h01123123, ImmSrcD : 6}  // UNKNOWN [FIXED]
    };
    
    i_ports input_cases;

    inst_extend dut(
        // input
        .inst(input_cases.inst),
        .ImmSrcD(input_cases.ImmSrcD),
        // output
        .ImmExtD(ImmExtD)
    );


    initial begin
        #3;

        foreach (case_lists[i]) begin
            input_cases = case_lists[i];
            $display("State : %0d", i);
            #3;
            case(i)
                IDLE : begin
                    if (ImmExtD == 32'h00000000) $display("Passed IDLE State");      // [FIXED] 0 → 32'h00000000
                    else $display("Failed IDLE State, %0h", ImmExtD);
                end
                I_type : begin
                    if (ImmExtD == 32'h00000012) $display("Passed I TYPE State");    // [FIXED]
                    else $display("Failed I TYPE State, %0h", ImmExtD);
                end
                S_type : begin
                    if (ImmExtD == 32'h00000006) $display("Passed S TYPE State");    // [FIXED]
                    else $display("Failed S TYPE State, %0h", ImmExtD);
                end
                B_type : begin
                    if (ImmExtD == 32'h00000002) $display("Passed B TYPE State");    // [FIXED]
                    else $display("Failed B TYPE State, %0h", ImmExtD);
                end
                U_type : begin
                    if (ImmExtD == 32'h00202000) $display("Passed U TYPE State");    // [FIXED]
                    else $display("Failed U TYPE State, %0h", ImmExtD);
                end
                J_type : begin
                    if (ImmExtD == 32'h00009012) $display("Passed J TYPE State");    // [FIXED]
                    else $display("Failed J TYPE State, %0h", ImmExtD);
                end
                UNKNOWN : begin
                    if (ImmExtD == 32'h00000000) $display("Passed UNKNOWN TYPE State");
                    else $display("Failed UNKNOWN TYPE State, %0h", ImmExtD);
                end
                default : begin
                    if (ImmExtD == 32'hzzzzzzzz) $display("Passed Default State");
                    else $display("Failed Default TYPE State, %0h", ImmExtD);
                end
            endcase
            #1;
        end
        #2;
        $finish;
    end


    initial begin
        $dumpfile("inst_extend_waveform.vcd");
        $dumpvars(0, dut);
    end

endmodule

RISCV32bit/Project_folder/Extend/inst_extended_vivado/inst_extended_vivado.sim/sim_1/behav/xsim/inst_extend_waveform.vcd
$date
   Wed Apr 15 05:48:14 2026
$end

$version
  2025.1.0
  $dumpfile ("inst_extend_waveform.vcd") 
$end

$timescale
  1ps
$end

$scope module tb_inst_extend $end
$scope module dut $end
$var wire 32 ! inst [31:0] $end
$var wire 3 " ImmSrcD [2:0] $end
$var wire 32 # ImmExtD [31:0] $end
$var reg 32 $ mem [31:0] $end
$upscope $end
$upscope $end
$enddefinitions $end

#0
$dumpvars
bx !
bx "
b0 #
b0 $
$end

#3000
b1001000110100010101100111 !
b0 "

#7000
b1001000110100001100100001 !
b1 "
b10010 #
b10010 $

#11000
b100100011001100100001 !
b10 "
b110 #
b110 $

#15000
b1100000001000100010011 !
b11 "
b10 #
b10 $

#19000
b1000000010001000110001 !
b100 "
b1000000010000000000000 #
b1000000010000000000000 $

#23000
b1001000001001001000001001 !
b101 "
b1001000000010010 #
b1001000000010010 $

#27000
b1000100100011000100100011 !
b110 "
b0 #
b0 $
